light_blue/__init__.py
light_blue/banner.py
light_blue/main.py
light_blue/passwordAuditor.py
light_blue/passwordChecker.py
light_blue/phishing_detector.py
light_blue/utils.py
light_blue_ep-1.1.0.dist-info/METADATA
light_blue_ep-1.1.0.dist-info/WHEEL
light_blue_ep-1.1.0.dist-info/entry_points.txt
light_blue_ep-1.1.0.dist-info/top_level.txt
light_blue_ep-1.1.0.dist-info/RECORD
