Metadata-Version: 2.4
Name: light-blue-ep
Version: 1.1.0
Summary: A terminal-based cybersecurity simulation game to learn password safety and phishing detection.
Author: Nithish Yenaganti
License: MIT
Classifier: Programming Language :: Python :: 3
Classifier: License :: OSI Approved :: MIT License
Classifier: Operating System :: OS Independent
Classifier: Intended Audience :: Education
Classifier: Topic :: Security
Classifier: Topic :: Games/Entertainment :: Simulation
Requires-Python: >=3.6
Requires-Dist: requests
Requires-Dist: python-dotenv
Requires-Dist: pyfiglet
Requires-Dist: colorama
Dynamic: author
Dynamic: classifier
Dynamic: description
Dynamic: description-content-type
Dynamic: license
Dynamic: requires-dist
Dynamic: requires-python
Dynamic: summary
